irisml_tasks_automl/__init__.py
irisml_tasks_automl/common/__init__.py
irisml_tasks_automl/common/base_config.py
irisml_tasks_automl/common/cost_estimator.py
irisml_tasks_automl/common/train_log.py
irisml_tasks_automl/controllers/__init__.py
irisml_tasks_automl/controllers/search_controller.py
irisml_tasks_automl/controllers/search_pruners.py
test/__init__.py
test/test_dict_config.py
test/test_search_controllers.py
test/test_search_pruner.py
irisml_tasks_automl-0.0.0.dist-info/LICENSE
irisml_tasks_automl-0.0.0.dist-info/METADATA
irisml_tasks_automl-0.0.0.dist-info/WHEEL
irisml_tasks_automl-0.0.0.dist-info/top_level.txt
irisml_tasks_automl-0.0.0.dist-info/RECORD
