Metadata-Version: 2.1
Name: irisml-tasks-automl
Version: 0.0.0
Summary: IrisML tasks for hyperparams tuning
Home-page: https://github.com/microsoft/irisml-tasks-automl
Author: irisdev
License: MIT
Requires-Python: >=3.8
License-File: LICENSE
